hyperpy/__init__.py
hyperpy/_version.py
hyperpy/raw.py
hyperpy/visualize.py
hyperpy/iari/__init__.py
hyperpy/iari/iari.py
hyperpy/utility/__init__.py
hyperpy/utility/utility.py
hyperpy-0.1.8.dist-info/LICENSE.txt
hyperpy-0.1.8.dist-info/METADATA
hyperpy-0.1.8.dist-info/WHEEL
hyperpy-0.1.8.dist-info/top_level.txt
hyperpy-0.1.8.dist-info/RECORD
