Metadata-Version: 2.1
Name: hyperpy
Version: 0.1.8
Summary: hyperpy: Scientific python library for Hyperspectral plant phenotyping and image processing.
Home-page: https://hyperpy.readthedocs.io/en/latest/
Author: Sunny Arya
Author-email: sunnyiniari@gmail.com
License: MIT
Keywords: plant phenotyping Hyperspectral Remote Sensing bioinformatics
Platform: Any
Classifier: License :: OSI Approved :: MIT License
Classifier: Programming Language :: Python :: 3.5
Classifier: Programming Language :: Python :: 3.6
Classifier: Programming Language :: Python :: 3.7
Classifier: Intended Audience :: Science/Research
Classifier: Topic :: Scientific/Engineering :: Image Recognition
Classifier: Topic :: Scientific/Engineering :: Information Analysis
Classifier: Topic :: Scientific/Engineering :: Bio-Informatics
Requires-Python: >=3.5
Requires-Dist: numpy (>=1.16)
Requires-Dist: spectral
Requires-Dist: matplotlib
